{
  "154": "花木兰",
  "123": "吕布",
  "141": "貂蝉",
  "121": "芈月",
  "167": "孙悟空",
  "169": "后羿",
  "168": "牛魔",
  "124": "周瑜",
  "128": "曹操",
  "130": "宫本武藏",
  "156": "张良",
  "146": "露娜",
  "166": "亚瑟",
  "142": "安琪拉",
  "107": "赵云",
  "110": "嬴政",
  "133": "狄仁杰",
  "135": "项羽",
  "111": "孙尚香",
  "116": "阿轲",
  "120": "白起",
  "109": "妲己",
  "108": "墨子",
  "119": "扁鹊",
  "144": "程咬金",
  "150": "韩信",
  "106": "小乔",
  "152": "王昭君",
  "129": "典韦",
  "115": "高渐离",
  "117": "钟无艳",
  "114": "刘禅",
  "139": "老夫子",
  "113": "庄周",
  "118": "孙膑",
  "136": "武则天",
  "126": "夏侯惇",
  "127": "甄姬",
  "112": "鲁班七号",
  "105": "廉颇",
  "134": "达摩",
  "148": "姜子牙",
  "131": "李白",
  "132": "马可波罗",
  "140": "关羽",
  "149": "刘邦",
  "153": "兰陵王",
  "155": "艾琳",
  "157": "不知火舞",
  "162": "娜可露露",
  "163": "橘右京",
  "170": "刘备",
  "171": "张飞",
  "173": "李元芳",
  "174": "虞姬",
  "175": "钟馗",
  "177": "成吉思汗",
  "178": "杨戬",
  "180": "哪吒",
  "183": "雅典娜",
  "184": "蔡文姬",
  "186": "太乙真人",
  "190": "诸葛亮",
  "191": "大乔",
  "192": "黄忠",
  "187": "东皇太一",
  "182": "干将莫邪",
  "189": "鬼谷子",
  "193": "铠",
  "196": "百里守约",
  "195": "百里玄策",
  "194": "苏烈",
  "198": "梦奇",
  "179": "女娲",
  "501": "明世隐",
  "199": "公孙离",
  "176": "杨玉环",
  "502": "裴擒虎",
  "197": "弈星",
  "503": "狂铁",
  "504": "米莱狄",
  "125": "元歌",
  "510": "孙策",
  "137": "司马懿",
  "509": "盾山",
  "508": "伽罗",
  "312": "沈梦溪",
  "507": "李信",
  "513": "上官婉儿",
  "515": "嫦娥",
  "511": "猪八戒",
  "529": "盘古",
  "505": "瑶",
  "506": "云中君",
  "522": "曜",
  "518": "马超",
  "523": "西施",
  "525": "鲁班大师",
  "524": "蒙犽",
  "531": "镜",
  "527": "蒙恬",
  "533": "阿古朵",
  "536": "夏洛特",
  "528": "澜",
  "537": "司空震"
}